{"track":{"no":5,"of":7},"disk":{"no":null,"of":null},"title":"Cowboy Song (for Martha)","album":"She Ate All The Pancake","year":2007,"encodedby":"iTunes v7.0.2","artists":["Robintone"],"artist":"Robintone","comment":["0"],"format":{"tagTypes":["ID3v2.2","ID3v1"],"lossless":false,"dataformat":"mp3","bitrate":160000,"sampleRate":44100,"numberOfChannels":2,"codecProfile":"CBR","numberOfSamples":8638848,"duration":195.8922448979592},"id":"8a83d2f5fddff9dd0381f22f15e6e43e","created":"2019-01-14T05:52:46.955Z","src":["8a83d2f5fddff9dd0381f22f15e6e43e.ogg","8a83d2f5fddff9dd0381f22f15e6e43e.mp3"]}